dconvert/__init__.py
dconvert/__main__.py
dconvert/cli.py
dconvert/dconvert.py
dconvert-1.0.dist-info/LICENSE
dconvert-1.0.dist-info/METADATA
dconvert-1.0.dist-info/WHEEL
dconvert-1.0.dist-info/entry_points.txt
dconvert-1.0.dist-info/top_level.txt
dconvert-1.0.dist-info/RECORD
