Metadata-Version: 2.1
Name: dconvert
Version: 1.0
Summary: A tool for converting data formats.
Home-page: https://github.com/aaronlmathis/dconvert
Author: Aaron Mathis
License: GPL-3.0
Classifier: Programming Language :: Python :: 3
Classifier: License :: OSI Approved :: GNU General Public License v3 (GPLv3)
Classifier: Operating System :: OS Independent
Requires-Python: >=3.6
License-File: LICENSE
Requires-Dist: et-xmlfile
Requires-Dist: lxml
Requires-Dist: numpy
Requires-Dist: openpyxl
Requires-Dist: pandas
Requires-Dist: python-dateutil
Requires-Dist: pytz
Requires-Dist: six
Requires-Dist: tzdata
